mhz14a/__init__.py
mhz14a/cli.py
mhz14a/exceptions.py
mhz14a/py.typed
mhz14a/sensor.py
mhz14a-0.1.3.dist-info/METADATA
mhz14a-0.1.3.dist-info/WHEEL
mhz14a-0.1.3.dist-info/entry_points.txt
mhz14a-0.1.3.dist-info/licenses/LICENSE
mhz14a-0.1.3.dist-info/RECORD
