Metadata-Version: 2.4
Name: mhz14a
Version: 0.1.3
Summary: Python library for MH-Z14A CO₂ sensor
Project-URL: Homepage, https://github.com/oaslananka/mhz14a-lib
Project-URL: Repository, https://github.com/oaslananka/mhz14a-lib.git
Project-URL: Issues, https://github.com/oaslananka/mhz14a-lib/issues
Project-URL: Documentation, https://github.com/oaslananka/mhz14a-lib#readme
Author-email: Osman Aslan <admin@oaslananka.me>
Maintainer-email: Osman Aslan <admin@oaslananka.me>
License-Expression: MIT
License-File: LICENSE
Keywords: co2,mhz14a,raspberry-pi,sensor,uart
Classifier: Development Status :: 4 - Beta
Classifier: Intended Audience :: Developers
Classifier: License :: OSI Approved :: MIT License
Classifier: Operating System :: OS Independent
Classifier: Programming Language :: Python :: 3
Classifier: Programming Language :: Python :: 3.8
Classifier: Programming Language :: Python :: 3.9
Classifier: Programming Language :: Python :: 3.10
Classifier: Programming Language :: Python :: 3.11
Classifier: Programming Language :: Python :: 3.12
Classifier: Topic :: Scientific/Engineering
Classifier: Topic :: System :: Hardware
Classifier: Typing :: Typed
Requires-Python: >=3.8
Requires-Dist: pyserial>=3.5
Provides-Extra: dev
Requires-Dist: build>=0.10.0; extra == 'dev'
Requires-Dist: mypy>=1.0.0; extra == 'dev'
Requires-Dist: pytest>=7.0.0; extra == 'dev'
Requires-Dist: ruff>=0.4.0; extra == 'dev'
